python_taxes/__init__.py
python_taxes/__main__.py
python_taxes/cli.py
python_taxes/federal/__init__.py
python_taxes/federal/income/__init__.py
python_taxes/federal/income/payroll/__init__.py
python_taxes/federal/income/payroll/automated.py
python_taxes/federal/income/tables/percentage/__init__.py
python_taxes/federal/income/tables/percentage/automated/__init__.py
python_taxes/federal/income/tables/percentage/automated/hoh.py
python_taxes/federal/income/tables/percentage/automated/married.py
python_taxes/federal/income/tables/percentage/automated/single.py
python_taxes/federal/medicare.py
python_taxes/federal/social_security.py
python_taxes-0.7.0.dist-info/METADATA
python_taxes-0.7.0.dist-info/WHEEL
python_taxes-0.7.0.dist-info/entry_points.txt
python_taxes-0.7.0.dist-info/licenses/LICENSE
python_taxes-0.7.0.dist-info/RECORD
