Metadata-Version: 2.4
Name: python-taxes
Version: 0.7.0
Summary: A Python library for calculating US Social Security, Medicare, and Federal Income taxes.
License: MIT License
License-File: LICENSE
Author: Stacy Noland
Author-email: 46572585+stacynoland@users.noreply.github.com
Requires-Python: >=3.10
Classifier: Development Status :: 4 - Beta
Classifier: Intended Audience :: Developers
Classifier: Intended Audience :: Information Technology
Classifier: License :: OSI Approved :: MIT License
Classifier: Operating System :: OS Independent
Classifier: Programming Language :: Python
Classifier: Programming Language :: Python :: 3
Classifier: Programming Language :: Python :: 3 :: Only
Classifier: Programming Language :: Python :: 3.10
Classifier: Programming Language :: Python :: 3.11
Classifier: Programming Language :: Python :: 3.12
Classifier: Programming Language :: Python :: 3.13
Classifier: Topic :: Software Development :: Libraries
Classifier: Topic :: Software Development :: Libraries :: Python Modules
Classifier: Typing :: Typed
Provides-Extra: cli
Requires-Dist: pydantic (>=2.11.3,<3.0.0)
Requires-Dist: typer (>=0.15.0,<1.0.0) ; extra == "cli"
Project-URL: Homepage, https://github.com/stacynoland/python-taxes
Project-URL: Source, https://github.com/stacynoland/python-taxes
